odoo/addons/stock_weighing_threaded_print/README.rst
odoo/addons/stock_weighing_threaded_print/__init__.py
odoo/addons/stock_weighing_threaded_print/__manifest__.py
odoo/addons/stock_weighing_threaded_print/i18n/stock_weighing_threaded_print.pot
odoo/addons/stock_weighing_threaded_print/models/__init__.py
odoo/addons/stock_weighing_threaded_print/models/stock_move_line.py
odoo/addons/stock_weighing_threaded_print/readme/CONFIGURE.rst
odoo/addons/stock_weighing_threaded_print/readme/CONTRIBUTORS.rst
odoo/addons/stock_weighing_threaded_print/readme/DESCRIPTION.rst
odoo/addons/stock_weighing_threaded_print/static/description/icon.png
odoo/addons/stock_weighing_threaded_print/static/description/index.html
odoo/addons/stock_weighing_threaded_print/wizards/__init__.py
odoo/addons/stock_weighing_threaded_print/wizards/weighing_wizard.py
odoo_addon_stock_weighing_threaded_print-15.0.1.0.1.dist-info/METADATA
odoo_addon_stock_weighing_threaded_print-15.0.1.0.1.dist-info/WHEEL
odoo_addon_stock_weighing_threaded_print-15.0.1.0.1.dist-info/top_level.txt
odoo_addon_stock_weighing_threaded_print-15.0.1.0.1.dist-info/RECORD
