Metadata-Version: 2.1
Name: odoo-addon-stock_weighing_threaded_print
Version: 15.0.1.0.1
Summary: Print labels on a different thread
Home-page: https://github.com/OCA/stock-weighing
Author: Tecnativa, Odoo Community Association (OCA)
Author-email: support@odoo-community.org
License: AGPL-3
Classifier: Programming Language :: Python
Classifier: Framework :: Odoo
Classifier: Framework :: Odoo :: 15.0
Classifier: License :: OSI Approved :: GNU Affero General Public License v3
Classifier: Development Status :: 4 - Beta
Requires-Python: >=3.8
Requires-Dist: odoo-addon-base-report-to-printer <15.1dev,>=15.0dev
Requires-Dist: odoo-addon-stock-weighing <15.1dev,>=15.0dev
Requires-Dist: odoo-addon-web-notify <15.1dev,>=15.0dev
Requires-Dist: odoo <15.1dev,>=15.0a
